ndx_odor_metadata/VERSION
ndx_odor_metadata/__init__.py
ndx_odor_metadata/utils.py
ndx_odor_metadata/spec/ndx-odor-metadata.extensions.yaml
ndx_odor_metadata/spec/ndx-odor-metadata.namespace.yaml
ndx_odor_metadata-0.1.1.dist-info/LICENSE.txt
ndx_odor_metadata-0.1.1.dist-info/METADATA
ndx_odor_metadata-0.1.1.dist-info/WHEEL
ndx_odor_metadata-0.1.1.dist-info/top_level.txt
ndx_odor_metadata-0.1.1.dist-info/RECORD
