Metadata-Version: 2.1
Name: ndx-odor-metadata
Version: 0.1.1
Summary: NWB Extension for documenting odor stimulus metadata
Author-email: Tuan Pham <tuanhpham@brown.edu>
Maintainer-email: Tuan Pham <tuanhpham@brown.edu>
License: BSD-3
Project-URL: Repository, https://gitlab.com/fleischmann-lab/ndx/ndx-odor-metadata
Project-URL: Homepage, https://gitlab.com/fleischmann-lab/ndx/ndx-odor-metadata
Project-URL: Bug Tracker, https://gitlab.com/fleischmann-lab/ndx/ndx-odor-metadata/-/issues
Project-URL: Documentation, https://fleischmann-lab.gitlab.io/ndx/ndx-odor-metadata/
Keywords: NeurodataWithoutBorders,NWB,nwb-extension,ndx-extension
Classifier: Intended Audience :: Developers
Classifier: Intended Audience :: Science/Research
Classifier: License :: OSI Approved :: BSD License
Classifier: Programming Language :: Python :: 3.8
Classifier: Programming Language :: Python :: 3.9
Classifier: Programming Language :: Python :: 3.10
Classifier: Programming Language :: Python :: 3.11
Requires-Python: >=3.8
License-File: LICENSE.txt
Requires-Dist: pynwb (<3,>=1.5.0)
Requires-Dist: hdmf (<4,>=3.4.7)
Requires-Dist: pubchempy (>=1.0.4)
Requires-Dist: pyyaml (>=5.0)
Requires-Dist: tqdm (>=4.0)
Provides-Extra: dev
Requires-Dist: black (>=22.0) ; extra == 'dev'
Requires-Dist: flake8 (>=6.0) ; extra == 'dev'
Requires-Dist: pytest (>=7.0) ; extra == 'dev'
Requires-Dist: isort (>=5.11) ; extra == 'dev'
Requires-Dist: pytest-subtests (==0.6.0) ; extra == 'dev'
Requires-Dist: hdmf-docutils (==0.4.4) ; extra == 'dev'
Requires-Dist: codespell ; extra == 'dev'
Requires-Dist: ipython ; extra == 'dev'
Requires-Dist: ipykernel ; extra == 'dev'
Requires-Dist: furo ; extra == 'dev'
Requires-Dist: pre-commit ; extra == 'dev'
